[
  {
    "cat": "warn",
    "kw": "kurve curve bend right rechts",
    "nameDe": "Kurve (rechts)",
    "nameEn": "Bend (right)",
    "stvo": "103-20",
    "en": "Sharp curve ahead — reduce speed before it.",
    "de": "Scharfe Kurve — vorher Tempo rausnehmen.",
    "tipEn": "Slow BEFORE the curve — speed kills on entry.",
    "tipDe": "Vor der Kurve bremsen — nicht in der Kurve.",
    "ar": "منعطف حاد يميناً — خفف السرعة قبله.",
    "tipAr": "الانعطاف: بطيء قبله، ثابت فيه، أسرع بعده."
  },
  {
    "cat": "warn",
    "kw": "kurve links left curve bend links links",
    "nameDe": "Kurve (links)",
    "nameEn": "Bend (left)",
    "stvo": "103-10",
    "en": "Sharp curve ahead — to the <b>left</b>. Slow before it.",
    "de": "Scharfe Kurve nach <b>links</b> — vorher Tempo rausnehmen.",
    "ar": "منعطف حاد إلى <b>اليسار</b> — خفف السرعة قبله.",
    "tipEn": "Mirror image of 103-20. Same rule: brake before entry.",
    "tipDe": "Spiegelbild von 103-20. Gleiche Regel: vor der Kurve bremsen.",
    "tipAr": "عكس 103-20 — نفس القاعدة: فرامل قبل المنعطف.",
    "drawn": "<svg viewBox=\"0 0 80 80\"><polygon points=\"40,7 76,69 4,69\" fill=\"#fff\" stroke=\"#d92f2f\" stroke-width=\"5.5\" stroke-linejoin=\"round\"/><path d=\"M45 63 L45 44 Q45 33 33 33 L33 27\" fill=\"none\" stroke=\"#111\" stroke-width=\"5\"/><path d=\"M33 22 l-7 9 14 0 z\" fill=\"#111\"/></svg>"
  },
  {
    "cat": "warn",
    "kw": "doppelkurve double bend zwei kurven s",
    "nameDe": "Doppelkurve",
    "nameEn": "Double bend",
    "stvo": "105-10",
    "en": "Series of bends, first one to the left.",
    "de": "Mehrere Kurven, erste nach links.",
    "tipEn": "S-shape: stay in your lane, resist speeding up mid-bend.",
    "tipDe": "S-Linie: in der Spur bleiben, kein Gasgeben in der Mitte.",
    "ar": "سلسلة منعطفات — الأول إلى اليسار.",
    "tipAr": "شكل S: ركّز ولا تعجل في المنتصف."
  },
  {
    "cat": "warn",
    "kw": "kreuzung crossroads junction vorfahrt von rechts",
    "nameDe": "Kreuzung",
    "nameEn": "Crossroads",
    "stvo": "102",
    "en": "Junction where <b>right-before-left</b> applies.",
    "de": "Kreuzung mit <b>rechts vor links</b>.",
    "tipEn": "No priority signs = give way to the right.",
    "tipDe": "Ohne Vorfahrtschild gilt: rechts hat Vorfahrt.",
    "ar": "تقاطع — قاعدة <b>اليمين قبل اليسار</b>.",
    "tipAr": "بلا إشارة أولوية = من اليمين له الأسبقية."
  },
  {
    "cat": "warn",
    "kw": "ampel lichtzeichen traffic light signals",
    "nameDe": "Lichtzeichenanlage",
    "nameEn": "Traffic signals ahead",
    "stvo": "131",
    "en": "Traffic lights coming up.",
    "de": "Ampel voraus.",
    "tipEn": "Ease off early — lights may be about to turn red.",
    "tipDe": "Tempo rausnehmen — Ampel könnte gleich umspringen.",
    "ar": "إشارات ضوئية قادمة.",
    "tipAr": "أبطئ مسبقاً — قد تكون على وشك التحول لأحمر."
  },
  {
    "cat": "warn",
    "kw": "fussganger pedestrians people gehweg",
    "nameDe": "Fußgänger",
    "nameEn": "Pedestrians",
    "stvo": "133-10",
    "en": "Expect people crossing — slow down.",
    "de": "Mit querenden Fußgängern rechnen.",
    "tipEn": "Pedestrians cross unexpectedly — treat as 30 zone.",
    "tipDe": "Fußgänger kreuzen unerwartet — wie 30er Zone behandeln.",
    "ar": "مشاة قد يعبرون — خفف السرعة.",
    "tipAr": "مشاة لا يرون السيارات جيداً في المنعطفات."
  },
  {
    "cat": "warn",
    "kw": "kinder children school schule",
    "nameDe": "Kinder",
    "nameEn": "Children",
    "stvo": "136-10",
    "en": "Schools / playgrounds — kids may run out.",
    "de": "Schule / Spielplatz — Kinder können auf die Straße laufen.",
    "tipEn": "Children don't judge speed — expect the unexpected.",
    "tipDe": "Kinder schätzen Entfernungen schlecht — auf Überraschungen gefasst sein.",
    "ar": "مدارس/ملاعب — أطفال قد يركضون فجأة.",
    "tipAr": "الأطفال لا يقيّمون المسافات — ابقَ منتبهاً."
  },
  {
    "cat": "warn",
    "kw": "radfahrer cyclists bike fahrrad",
    "nameDe": "Radverkehr",
    "nameEn": "Cyclists crossing",
    "stvo": "138-10",
    "en": "Cyclists may cross or join the road.",
    "de": "Radfahrer können kreuzen/einfahren.",
    "tipEn": "Mirror + blind-spot check before every right turn.",
    "tipDe": "Spiegel + Schulterblick vor jedem Rechtsabbiegen.",
    "ar": "دراجون قد يعبرون أو يلتحقون بالطريق.",
    "tipAr": "راجع المرايا والزاوية العمياء عند الانعطاف يميناً."
  },
  {
    "cat": "warn",
    "kw": "wild tiere deer animals wildwechsel",
    "nameDe": "Wildwechsel",
    "nameEn": "Wild animals",
    "stvo": "142-10",
    "en": "Animals may cross — common at dawn/dusk.",
    "de": "Wildwechsel — oft in der Dämmerung.",
    "tipEn": "If you see one, expect more behind it. Brake, scan.",
    "tipDe": "Eins sehen = mehr dahinter. Bremsen, scannen.",
    "ar": "حيوانات برية قد تعبر — شائعة عند الفجر والغروب.",
    "tipAr": "إذا رأيت واحداً توقف — يأتون في قطعان."
  },
  {
    "cat": "warn",
    "kw": "baustelle roadworks construction arbeit",
    "nameDe": "Baustelle",
    "nameEn": "Roadworks",
    "stvo": "123",
    "en": "Construction site ahead.",
    "de": "Baustelle voraus.",
    "tipEn": "Fines are doubled inside active construction zones.",
    "tipDe": "Bußgelder innerhalb der Baustelle verdoppelt.",
    "ar": "موقع بناء قادم.",
    "tipAr": "الغرامات تُضاعف داخل مواقع البناء."
  },
  {
    "cat": "warn",
    "kw": "schleudergefahr slippery glatt nass slip",
    "nameDe": "Schleudergefahr",
    "nameEn": "Slippery road",
    "stvo": "114",
    "en": "Risk of skidding (wet, ice, leaves).",
    "de": "Schleuder-/Rutschgefahr.",
    "tipEn": "Stopping distance doubles on wet road — double your gap.",
    "tipDe": "Bremsweg verdoppelt sich auf nasser Fahrbahn — Abstand verdoppeln.",
    "ar": "خطر الانزلاق (مطر، جليد، أوراق شجر).",
    "tipAr": "مسافة التوقف تتضاعف على الطريق الرطب."
  },
  {
    "cat": "warn",
    "kw": "verengte fahrbahn road narrows eng",
    "nameDe": "Verengte Fahrbahn",
    "nameEn": "Road narrows",
    "stvo": "120",
    "en": "Carriageway gets narrower (both sides).",
    "de": "Fahrbahn wird enger (beidseitig).",
    "tipEn": "The vehicle with more room usually goes first.",
    "tipDe": "Das Fahrzeug mit mehr Platz fährt meistens zuerst.",
    "ar": "الطريق يضيق — تنبه للمركبات القادمة.",
    "tipAr": "من له الامتداد الأكبر عادةً له الأولوية في المرور."
  },
  {
    "cat": "warn",
    "kw": "gegenverkehr two way oncoming",
    "nameDe": "Gegenverkehr",
    "nameEn": "Two-way traffic",
    "stvo": "125",
    "en": "Oncoming traffic returns (end of one-way/dual).",
    "de": "Gegenverkehr (Ende Einbahn/Trennung).",
    "tipEn": "Stay in your lane — two-way traffic resumes.",
    "tipDe": "In der Spur bleiben — Gegenverkehr beginnt wieder.",
    "ar": "مركبات قادمة — نهاية الاتجاه الواحد أو الفاصل.",
    "tipAr": "ابقَ في مسارك — السيارات تعود لاتجاهين."
  },
  {
    "cat": "warn",
    "kw": "gefalle steigung hill steep berg downhill",
    "nameDe": "Gefälle",
    "nameEn": "Steep descent",
    "stvo": "108-10",
    "en": "Steep downhill — engine-brake, keep distance.",
    "de": "Starkes Gefälle — mit Motor bremsen, Abstand halten.",
    "tipEn": "Continuous braking overheats brakes. Use a lower gear.",
    "tipDe": "Dauerbremsung überhitzt — einen Gang runterschalten.",
    "ar": "منحدر حاد — استخدم فرامل المحرك واحتفظ بالمسافة.",
    "tipAr": "الفرامل المستمرة تسخن وتفشل — استخدم نيراً أدنى."
  },
  {
    "cat": "warn",
    "kw": "steigung steep hill uphill ascent berg anstieg",
    "nameDe": "Steigung",
    "nameEn": "Steep ascent",
    "stvo": "110-10",
    "en": "Steep uphill — downshift early, watch brakes on descent.",
    "de": "Starke Steigung — früh zurückschalten, auf Gefälle danach vorbereiten.",
    "ar": "منحدر صاعد حاد — انزل نيراً مبكراً واحذر الهبوط بعده.",
    "tipEn": "Climb slowly = arrive at the top in control for the descent.",
    "tipDe": "Langsam hinauf = oben am Gefälle gut vorbereitet sein.",
    "tipAr": "تسلّق ببطء = تصل القمة مستعداً للهبوط.",
    "drawn": "<svg viewBox=\"0 0 80 80\"><polygon points=\"40,7 76,69 4,69\" fill=\"#fff\" stroke=\"#d92f2f\" stroke-width=\"5.5\" stroke-linejoin=\"round\"/><path d=\"M24 60 L56 38\" stroke=\"#111\" stroke-width=\"5\"/><text x=\"40\" y=\"32\" font-size=\"13\" font-weight=\"800\" fill=\"#111\" text-anchor=\"middle\">10%</text></svg>"
  },
  {
    "cat": "warn",
    "kw": "bahnubergang level crossing zug train schranke",
    "nameDe": "Bahnübergang",
    "nameEn": "Level crossing",
    "stvo": "150",
    "en": "Railway crossing with barriers ahead.",
    "de": "Beschrankter Bahnübergang.",
    "tipEn": "A train needs 1 km to stop. It cannot avoid you.",
    "tipDe": "Ein Zug braucht 1 km zum Bremsen. Er kann nicht ausweichen.",
    "ar": "معبر سككي بحواجز — توقف إذا أومضت الأضواء.",
    "tipAr": "احتسب: القطار يحتاج 1 كم للتوقف — لا مجال للمجازفة."
  },
  {
    "cat": "warn",
    "kw": "gefahrstelle general danger achtung allgemein",
    "nameDe": "Gefahrstelle",
    "nameEn": "General danger",
    "stvo": "101",
    "en": "Unspecified danger — a plate usually says what.",
    "de": "Allgemeine Gefahr — Zusatzschild sagt meist was.",
    "tipEn": "Always check the supplementary plate below for details.",
    "tipDe": "Immer das Zusatzschild darunter lesen.",
    "ar": "خطر غير محدد — لوحة إضافية توضح النوع.",
    "tipAr": "تحقق دائماً من اللوحة الإضافية أسفله."
  },
  {
    "cat": "warn",
    "kw": "stau congestion traffic jam",
    "nameDe": "Stau",
    "nameEn": "Traffic queues",
    "stvo": "124",
    "en": "Jam likely — hazard lights help warn those behind.",
    "de": "Staugefahr — Warnblinker warnt den Verkehr hinter dir.",
    "tipEn": "Hazard lights at queue end warn traffic behind you.",
    "tipDe": "Warnblinker am Stauende — Warnung für nachfolgende Autos.",
    "ar": "ازدحام مروري محتمل — شغّل وامضات الطوارئ عند التوقف.",
    "tipAr": "وامضات الطوارئ في نهاية الطابور — تحذير للقادمين خلفك."
  },
  {
    "cat": "warn",
    "kw": "seitenwind crosswind windsack",
    "nameDe": "Seitenwind",
    "nameEn": "Crosswind",
    "stvo": "117-10",
    "en": "Gusts push you sideways — grip the wheel, slow down.",
    "de": "Böen versetzen das Auto — festhalten, langsamer.",
    "tipEn": "High-sided vehicles and bikes are worst hit by gusts.",
    "tipDe": "Transporter und Motorräder am stärksten betroffen.",
    "ar": "رياح جانبية — تمسك بالمقود بقوة.",
    "tipAr": "الشاحنات والمركبات العالية تتأثر أكثر."
  },
  {
    "cat": "warn",
    "kw": "steinschlag falling rocks felsen",
    "nameDe": "Steinschlag",
    "nameEn": "Falling rocks",
    "stvo": "115",
    "en": "Rocks may be on the road — watch the surface.",
    "de": "Steine können auf der Fahrbahn liegen.",
    "tipEn": "Don't swerve hard — slow, steer carefully around debris.",
    "tipDe": "Nicht scharf ausweichen — abbremsen, behutsam umfahren.",
    "ar": "صخور قد تكون على الطريق — راقب السطح.",
    "tipAr": "لا تتفادى فجأة — تباطأ ومُرَّ بعناية."
  },
  {
    "cat": "warn",
    "kw": "schnee eisglatte ice snow glaette",
    "nameDe": "Schnee- oder Eisglätte",
    "nameEn": "Snow / ice",
    "stvo": "113",
    "en": "Icy stretch likely (bridges freeze first).",
    "de": "Glättegefahr (Brücken frieren zuerst).",
    "tipEn": "Ice: stopping distance up to 10× longer. Huge gap.",
    "tipDe": "Eis: bis zu 10-facher Bremsweg. Sehr großen Abstand halten.",
    "ar": "خطر الجليد والزلق — الجسور تتجمد أولاً.",
    "tipAr": "مسافة التوقف تتضاعف 10 مرات على الجليد."
  },
  {
    "cat": "warn",
    "kw": "unebenheit uneven road bump hump schlagloch rumpel",
    "nameDe": "Unebenheit",
    "nameEn": "Uneven road",
    "stvo": "112",
    "en": "Bumpy surface or road hump — reduce speed to protect tyres.",
    "de": "Unebenheit oder Bodenschwelle — Tempo rausnehmen, Reifen schonen.",
    "ar": "سطح وعر أو مطب — خفف السرعة لحماية الإطارات.",
    "tipEn": "Hitting a bump at speed can cause loss of control. Ease off.",
    "tipDe": "Mit Schwung über eine Bodenschwelle = Kontrolle verlieren. Abbremsen.",
    "tipAr": "الاصطدام بمطب بسرعة = فقدان السيطرة — خفف.",
    "drawn": "<svg viewBox=\"0 0 80 80\"><polygon points=\"40,7 76,69 4,69\" fill=\"#fff\" stroke=\"#d92f2f\" stroke-width=\"5.5\" stroke-linejoin=\"round\"/><path d=\"M22 56 Q28 44 34 52 Q40 60 46 48 Q52 36 58 44\" fill=\"none\" stroke=\"#111\" stroke-width=\"5\" stroke-linecap=\"round\"/></svg>"
  },
  {
    "cat": "warn",
    "kw": "bahnubergang ohne schranken unbeschrankt train no barrier",
    "nameDe": "Bahnübergang ohne Schranken",
    "nameEn": "Crossing, no barriers",
    "stvo": "151",
    "en": "Unguarded rail crossing — look and listen yourself.",
    "de": "Unbeschrankt — selbst schauen und hören.",
    "tipEn": "No signals here. Slow, look both ways, listen.",
    "tipDe": "Keine Ampel. Langsam, beide Seiten schauen, hören.",
    "ar": "معبر سككي بلا حواجز — أنت من يراقب ويسمع.",
    "tipAr": "تباطأ، انظر، استمع — لا إشارة ضوئية تحميك."
  },
  {
    "cat": "warn",
    "kw": "baken countdown beacons bahnubergang 240 160 80",
    "nameDe": "Baken",
    "nameEn": "Countdown beacons",
    "stvo": "156-10",
    "en": "3 / 2 / 1 stripes = 240 / 160 / 80 m to the crossing.",
    "de": "3 / 2 / 1 Streifen = 240 / 160 / 80 m bis zum Übergang.",
    "tipEn": "Each stripe removed = 80 m closer. Begin slowing at 3.",
    "tipDe": "Jeder Streifen weniger = 80 m näher. Bei 3 Streifen bremsen.",
    "ar": "3 / 2 / 1 شريط = 240 / 160 / 80 متر للمعبر.",
    "tipAr": "كل شريط تُزيل = 80 متراً — ابدأ بالتوقف عند 3."
  }
]